odoo/addons/fieldservice_sale_stock_route/README.rst
odoo/addons/fieldservice_sale_stock_route/__init__.py
odoo/addons/fieldservice_sale_stock_route/__manifest__.py
odoo/addons/fieldservice_sale_stock_route/i18n/ca.po
odoo/addons/fieldservice_sale_stock_route/i18n/es.po
odoo/addons/fieldservice_sale_stock_route/i18n/fieldservice_sale_stock_route.pot
odoo/addons/fieldservice_sale_stock_route/models/__init__.py
odoo/addons/fieldservice_sale_stock_route/models/fsm_order.py
odoo/addons/fieldservice_sale_stock_route/models/fsm_route.py
odoo/addons/fieldservice_sale_stock_route/models/fsm_route_dayroute.py
odoo/addons/fieldservice_sale_stock_route/models/sale_order.py
odoo/addons/fieldservice_sale_stock_route/readme/CONTRIBUTORS.rst
odoo/addons/fieldservice_sale_stock_route/readme/DESCRIPTION.rst
odoo/addons/fieldservice_sale_stock_route/readme/USAGE.rst
odoo/addons/fieldservice_sale_stock_route/static/description/icon.png
odoo/addons/fieldservice_sale_stock_route/static/description/index.html
odoo/addons/fieldservice_sale_stock_route/tests/__init__.py
odoo/addons/fieldservice_sale_stock_route/tests/test_fieldservice_sale_stock_route.py
odoo/addons/fieldservice_sale_stock_route/views/fsm_order.xml
odoo/addons/fieldservice_sale_stock_route/views/fsm_route.xml
odoo/addons/fieldservice_sale_stock_route/views/sale_order.xml
odoo_addon_fieldservice_sale_stock_route-15.0.1.0.5.dist-info/METADATA
odoo_addon_fieldservice_sale_stock_route-15.0.1.0.5.dist-info/WHEEL
odoo_addon_fieldservice_sale_stock_route-15.0.1.0.5.dist-info/top_level.txt
odoo_addon_fieldservice_sale_stock_route-15.0.1.0.5.dist-info/RECORD
