Metadata-Version: 2.1
Name: odoo-addon-fieldservice_sale_stock_route
Version: 15.0.1.0.5
Summary: Link between Field Service Sale Stock and Route
Home-page: https://github.com/OCA/field-service
Author: APSL-Nagarro, Odoo Community Association (OCA)
Author-email: support@odoo-community.org
License: AGPL-3
Classifier: Programming Language :: Python
Classifier: Framework :: Odoo
Classifier: Framework :: Odoo :: 15.0
Classifier: License :: OSI Approved :: GNU Affero General Public License v3
Requires-Python: >=3.8
Requires-Dist: odoo-addon-fieldservice-route<15.1dev,>=15.0dev
Requires-Dist: odoo-addon-fieldservice-sale-stock<15.1dev,>=15.0dev
Requires-Dist: odoo<15.1dev,>=15.0a
